external_data_loader/__init__.py
external_data_loader/__main__.py
external_data_loader/constants.py
external_data_loader/opti_api.py
external_data_loader/pim_api.py
external_data_loader-0.0.12.dist-info/METADATA
external_data_loader-0.0.12.dist-info/WHEEL
external_data_loader-0.0.12.dist-info/licenses/LICENSE
external_data_loader-0.0.12.dist-info/RECORD
