Metadata-Version: 2.4
Name: external_data_loader
Version: 0.0.12
Author-email: David Momeni <dav.momeni@gmail.com>
License-File: LICENSE
Classifier: License :: OSI Approved :: MIT License
Classifier: Operating System :: OS Independent
Classifier: Programming Language :: Python :: 3
Requires-Python: >=3.8
Requires-Dist: requests
Requires-Dist: rusta-tools
